developeralex_openai_without_pydantic-0.1.0.dist-info/licenses/LICENSE
openai_wrapper/__init__.py
openai_wrapper/client.py
openai_wrapper/py.typed
developeralex_openai_without_pydantic-0.1.0.dist-info/METADATA
developeralex_openai_without_pydantic-0.1.0.dist-info/WHEEL
developeralex_openai_without_pydantic-0.1.0.dist-info/top_level.txt
developeralex_openai_without_pydantic-0.1.0.dist-info/RECORD
