Metadata-Version: 2.4
Name: developeralex-openai-without-pydantic
Version: 0.1.0
Summary: A simple Python wrapper for OpenAI API without Pydantic dependencies
Home-page: https://github.com/DeveloperAlex/pypi_OpenAI_Without_Pydantic
Author: DeveloperAlex
Author-email: 
Maintainer: DeveloperAlex
License: MIT
Project-URL: Homepage, https://github.com/DeveloperAlex/pypi_OpenAI_Without_Pydantic
Project-URL: Documentation, https://github.com/DeveloperAlex/pypi_OpenAI_Without_Pydantic#readme
Project-URL: Repository, https://github.com/DeveloperAlex/pypi_OpenAI_Without_Pydantic
Project-URL: Bug Reports, https://github.com/DeveloperAlex/pypi_OpenAI_Without_Pydantic/issues
Keywords: openai,api,wrapper,pydantic-free,no-pydantic,ai,llm,gpt
Classifier: Development Status :: 4 - Beta
Classifier: Intended Audience :: Developers
Classifier: Topic :: Software Development :: Libraries :: Python Modules
Classifier: Topic :: Scientific/Engineering :: Artificial Intelligence
Classifier: License :: OSI Approved :: MIT License
Classifier: Programming Language :: Python :: 3
Classifier: Programming Language :: Python :: 3.10
Classifier: Programming Language :: Python :: 3.11
Classifier: Programming Language :: Python :: 3.12
Classifier: Operating System :: OS Independent
Requires-Python: >=3.7
License-File: LICENSE
Requires-Dist: requests>=2.25.0
Provides-Extra: dev
Requires-Dist: python-dotenv>=0.19.0; extra == "dev"
Requires-Dist: pytest>=7.0.0; extra == "dev"
Requires-Dist: pytest-cov>=3.0.0; extra == "dev"
Dynamic: home-page
Dynamic: license-file
Dynamic: requires-python
